{"esfp // the entertainer ": "4pi2j0t6uT4YtBXnT2gAa4", "estp // the rule breaker ": "4OnGyVyLPdmBev3HBT0tYu", "isfp // the creative": "4phCnknfZ5LhEYmArdUJXv", "istp // the prodigy ": "3RqQRynMWJoP9JkEc7YrOE", "esfj // the authentic ": "3aVsLjJaHunrEhlVRp9AxT", "estj // the administrator ": "1KIdUNGcJLOPTkewJimsQ7", "isfj // the protector ": "3ZXgVNRlimnET5ceMz7XXQ", "istj // the logistician ": "00Ni0Ve2XMw43uPE6g73RN", "enfp // the individualist ": "5GQ1YxFYw0pxC9LmAVcCXZ", "enfj // the protagonist ": "6th4JW4Dky7UjeEhHuQeQd", "entp // the debater ": "4RdPgciqwk1Pzo8OXKVCZB", "entj // the commander ": "2L6Dxf2WAqoIQX50Zg4wFR", "intp // the scholar": "3g57PuPnoAVo1lfJhQZeDj", "intj // the architect ": "0qBVUmdHvl7vaQnNtQatlC", "infp // the mediator": "5TW1TKTM7Q99Z3p4NvtReA", "infj // the visionary ": "2fHK41mb288anu6dQDNuB8"}